{
  "main": {
    "id": "3fef808d646bc30d",
    "type": "split",
    "children": [
      {
        "id": "ea0b46ece4020c55",
        "type": "tabs",
        "children": [
          {
            "id": "58ce9664dd39dbc7",
            "type": "leaf",
            "state": {
              "type": "markdown",
              "state": {
                "file": "src/content/post/rust-aoc-day-01.md",
                "mode": "source",
                "source": false
              }
            }
          }
        ]
      }
    ],
    "direction": "vertical"
  },
  "left": {
    "id": "d173c9d3aa154d09",
    "type": "split",
    "children": [
      {
        "id": "59eef2d1470697b3",
        "type": "tabs",
        "children": [
          {
            "id": "5919a37ccee6cc78",
            "type": "leaf",
            "state": {
              "type": "file-explorer",
              "state": {
                "sortOrder": "alphabetical"
              }
            }
          },
          {
            "id": "effb05fb51ed6791",
            "type": "leaf",
            "state": {
              "type": "search",
              "state": {
                "query": "",
                "matchingCase": false,
                "explainSearch": false,
                "collapseAll": false,
                "extraContext": false,
                "sortOrder": "alphabetical"
              }
            }
          },
          {
            "id": "de4287a9e9159af9",
            "type": "leaf",
            "state": {
              "type": "bookmarks",
              "state": {}
            }
          }
        ]
      }
    ],
    "direction": "horizontal",
    "width": 300
  },
  "right": {
    "id": "b9da8a232c7f6d6e",
    "type": "split",
    "children": [
      {
        "id": "706eacf9d36978b8",
        "type": "tabs",
        "children": [
          {
            "id": "f6b9ae928b1449f6",
            "type": "leaf",
            "state": {
              "type": "backlink",
              "state": {
                "file": "src/content/post/rust-aoc-day-01.md",
                "collapseAll": false,
                "extraContext": false,
                "sortOrder": "alphabetical",
                "showSearch": false,
                "searchQuery": "",
                "backlinkCollapsed": false,
                "unlinkedCollapsed": true
              }
            }
          },
          {
            "id": "44979fe68ed603ea",
            "type": "leaf",
            "state": {
              "type": "outgoing-link",
              "state": {
                "file": "src/content/post/rust-aoc-day-01.md",
                "linksCollapsed": false,
                "unlinkedCollapsed": true
              }
            }
          },
          {
            "id": "b1871beef94d3f86",
            "type": "leaf",
            "state": {
              "type": "tag",
              "state": {
                "sortOrder": "frequency",
                "useHierarchy": true
              }
            }
          },
          {
            "id": "fe966f7194870c8b",
            "type": "leaf",
            "state": {
              "type": "outline",
              "state": {
                "file": "src/content/post/rust-aoc-day-01.md"
              }
            }
          }
        ]
      }
    ],
    "direction": "horizontal",
    "width": 300,
    "collapsed": true
  },
  "left-ribbon": {
    "hiddenItems": {
      "switcher:Open quick switcher": false,
      "graph:Open graph view": false,
      "canvas:Create new canvas": false,
      "daily-notes:Open today's daily note": false,
      "templates:Insert template": false,
      "command-palette:Open command palette": false
    }
  },
  "active": "58ce9664dd39dbc7",
  "lastOpenFiles": [
    "src/content/post/mutability-in-rust.md"
  ]
}